{
  "id": "b6474424471e6c4212fae0aef6021e75",
  "route": "/servicos",
  "title": "Serviços",
  "blocks": [
    {
      "id": "fdbd39916992bef06b9c315ad332aa0e",
      "type": "hero",
      "content": {
        "title": "Bem-vindo",
        "subtitle": "Esta é uma página nova criada no Editor Visual",
        "backgroundImage": "",
        "buttonText": "Saiba Mais",
        "buttonLink": "#"
      },
      "styles": {
        "backgroundColor": "#0a0a0a",
        "textColor": "#ffffff",
        "padding": "4rem 1rem",
        "textAlign": "center"
      },
      "position": 0
    }
  ],
  "metadata": {
    "seoTitle": "DOMREALCE",
    "seoDescription": "Comunicação visual e impressão digital em Portugal",
    "keywords": "comunicação visual, impressão digital, design gráfico"
  },
  "version": 1,
  "status": "draft",
  "updatedAt": "2025-09-15T08:27:42.967Z"
}